mktemplate/__init__.py
mktemplate/mktemplate.py
mkdocs_mktemplate_plugin-1.0.1.dist-info/LICENSE
mkdocs_mktemplate_plugin-1.0.1.dist-info/METADATA
mkdocs_mktemplate_plugin-1.0.1.dist-info/WHEEL
mkdocs_mktemplate_plugin-1.0.1.dist-info/entry_points.txt
mkdocs_mktemplate_plugin-1.0.1.dist-info/top_level.txt
mkdocs_mktemplate_plugin-1.0.1.dist-info/RECORD
