Metadata-Version: 2.1
Name: mkdocs-mktemplate-plugin
Version: 1.0.1
Summary: mkdocs plugin to insert jinja templates on any page
Home-page: https://github.com/fiinnnn/mkdocs-mktemplate-plugin
Author: Finn Vos
License: MIT
Platform: UNKNOWN
License-File: LICENSE
Requires-Dist: mkdocs
Requires-Dist: Jinja2
Requires-Dist: PyYAML
